[
    {
        "itemImageUrl": "https://i.ibb.co/Lz5M8wM/Rockhide.png",
        "itemTitle": "Rockhide",
        "itemDescription": "This is the story of a cunning rogue in a fictional game world.",
        "itemRating": "4.9"
    },
    {
        "itemImageUrl": "https://i.ibb.co/Sfnv746/Soulreaver.png",
        "itemTitle": "Soulreaver",
        "itemDescription": "This is the story of a brave knight in a fictional game world.",
        "itemRating": "4.0"
    },
    {
        "itemImageUrl": "https://i.ibb.co/5FwjTws/Doomwing.png",
        "itemTitle": "Doomwing",
        "itemDescription": "This is the story of an agile archer in a fictional game world.",
        "itemRating": "3.9"
    },
    {
        "itemImageUrl": "https://i.ibb.co/fdVcKQj/Dreadmaw.png",
        "itemTitle": "Dreadmaw",
        "itemDescription": "This is the story of a brave knight in a fictional game world.",
        "itemRating": "4.8"
    },
    {
        "itemImageUrl": "https://i.ibb.co/2vfFZLL/Swampcrawler.png",
        "itemTitle": "Swampcrawler",
        "itemDescription": "This is the story of a powerful warlock in a fictional game world.",
        "itemRating": "4.2"
    },
    {
        "itemImageUrl": "https://i.ibb.co/PTBbZz7/Mudmaw.png",
        "itemTitle": "Mudmaw",
        "itemDescription": "This is the story of a wise wizard in a fictional game world.",
        "itemRating": "4.9"
    },
    {
        "itemImageUrl": "https://i.ibb.co/wYrqqxD/Venomtail.png",
        "itemTitle": "Venomtail",
        "itemDescription": "This is the story of a wise wizard in a fictional game world.",
        "itemRating": "4.9"
    },
    {
        "itemImageUrl": "https://i.ibb.co/k1Pq3NZ/Grimclaw.png",
        "itemTitle": "Grimclaw",
        "itemDescription": "This is the story of a cunning rogue in a fictional game world.",
        "itemRating": "3.8"
    },
    {
        "itemImageUrl": "https://i.ibb.co/wysJ6s5/Thornhide.png",
        "itemTitle": "Thornhide",
        "itemDescription": "This is the story of a powerful warlock in a fictional game world.",
        "itemRating": "4.0"
    },
    {
        "itemImageUrl": "https://i.ibb.co/HPSCJxQ/Stormbeak.png",
        "itemTitle": "Stormbeak",
        "itemDescription": "This is the story of an agile archer in a fictional game world.",
        "itemRating": "4.4"
    },
    {
        "itemImageUrl": "https://i.ibb.co/QmHCFwp/Frostfang.png",
        "itemTitle": "Frostfang",
        "itemDescription": "This is the story of a wise wizard in a fictional game world.",
        "itemRating": "4.4"
    },
    {
        "itemImageUrl": "https://i.ibb.co/M7cDy3g/Nightshade.png",
        "itemTitle": "Nightshade",
        "itemDescription": "This is the story of a powerful warlock in a fictional game world.",
        "itemRating": 4.9
    },
    {
        "itemImageUrl": "https://i.ibb.co/yfMctft/Abyssal.png",
        "itemTitle": "Abyssal",
        "itemDescription": "This is the story of a brave knight in a fictional game world.",
        "itemRating": "4.6"
    },
    {
        "itemImageUrl": "https://i.ibb.co/rGTFmXc/Vilebloom.png",
        "itemTitle": "Vilebloom",
        "itemDescription": "This is the story of a cunning rogue in a fictional game world.",
        "itemRating": "4.9"
    },
    {
        "itemImageUrl": "https://i.ibb.co/DYZjWJC/Spectral.png",
        "itemTitle": "Spectral",
        "itemDescription": "This is the story of a powerful warlock in a fictional game world.",
        "itemRating": "4.8"
    },
    {
        "itemImageUrl": "https://i.ibb.co/xmmcmd4/Emberdrake.png",
        "itemTitle": "Emberdrake",
        "itemDescription": "This is the story of a skilled assassin in a fictional game world.",
        "itemRating": "4.1"
    },
    {
        "itemImageUrl": "https://i.ibb.co/SfDkpFp/Bloodhorn.png",
        "itemTitle": "Bloodhorn",
        "itemDescription": "This is the story of a cunning rogue in a fictional game world.",
        "itemRating": "3.9"
    },
    {
        "itemImageUrl": "https://i.ibb.co/ZNpcC7K/Blightwing.png",
        "itemTitle": "Blightwing",
        "itemDescription": "This is the story of a cunning rogue in a fictional game world.",
        "itemRating": "4.6"
    }
]
